{
  "generated_at": "2026-07-09 19:05",
  "trade_date": "2026-07-09",
  "session": "1520",
  "session_name": "15:20 盘后选池",
  "analysis_run_id": 1,
  "market_regime": {
    "trade_date": "2026-07-09",
    "above_ma20_ratio": 0.5333333333333333,
    "ma20_slope_positive_ratio": 0.7333333333333333,
    "inflow_positive_ratio": 0.6,
    "regime": "RECOVERY"
  },
  "trading_permission": {
    "can_open": true,
    "max_exposure_pct": 0.25,
    "max_positions": 2,
    "theme_enabled": true,
    "daily_new_allowed": true,
    "trend_down_exit_days": 3
  },
  "guardrails": {
    "train_capital": 30000,
    "first_entry_ratio": 0.33,
    "max_total_exposure_pct": 0.25,
    "max_single_etf_pct": 0.2,
    "theme_position_pct": 0,
    "trend_down_exit_days": 3
  },
  "focus_watch": [
    {
      "code": "512760",
      "name": "半导体ETF",
      "category": "THEME",
      "score": 36.63,
      "price": 1.55,
      "pct": 9.77,
      "main_inflow": 254374234.0,
      "main_inflow_pct": 20.26,
      "ma5": 1.4365999999999999,
      "ma10": 1.4731999999999998,
      "ma20": 1.3744999999999998,
      "amount_ratio_20": null,
      "reason": "通过硬过滤；OBSERVE_ONLY",
      "trigger": "09:40后站稳VWAP/MA5且主力资金保持为正",
      "failure": "资金转负或跌破MA5；跌破MA10退出观察",
      "suggested_action": "observe_only_or_first_1_3"
    },
    {
      "code": "515070",
      "name": "AI ETF",
      "category": "THEME",
      "score": 25.12,
      "price": 1.379,
      "pct": 6.4,
      "main_inflow": 26411712.0,
      "main_inflow_pct": 8.32,
      "ma5": 1.3052,
      "ma10": 1.324,
      "ma20": 1.3012000000000001,
      "amount_ratio_20": null,
      "reason": "通过硬过滤；OBSERVE_ONLY",
      "trigger": "09:40后站稳VWAP/MA5且主力资金保持为正",
      "failure": "资金转负或跌破MA5；跌破MA10退出观察",
      "suggested_action": "observe_only_or_first_1_3"
    },
    {
      "code": "510050",
      "name": "上证50ETF",
      "category": "CORE",
      "score": 18.76,
      "price": 3.089,
      "pct": 2.66,
      "main_inflow": 215266400.0,
      "main_inflow_pct": 10.43,
      "ma5": 3.036,
      "ma10": 3.0423,
      "ma20": 3.02835,
      "amount_ratio_20": null,
      "reason": "通过硬过滤；OBSERVE_ONLY",
      "trigger": "09:40后站稳VWAP/MA5且主力资金保持为正",
      "failure": "资金转负或跌破MA5；跌破MA10退出观察",
      "suggested_action": "observe_only_or_first_1_3"
    }
  ],
  "wait": [
    {
      "code": "589020",
      "name": "KC半导体",
      "category": "THEME",
      "score": 24.8,
      "price": 3.391,
      "pct": 10.1,
      "main_inflow": -81153610.0,
      "main_inflow_pct": -7.12,
      "ma5": 3.055,
      "ma10": 3.1182000000000003,
      "ma20": 2.7908,
      "amount_ratio_20": null,
      "reason": "主力资金未转正；OBSERVE_ONLY",
      "trigger": "等待资金转正并站回MA5",
      "failure": "继续跌破MA10或放量长阴",
      "suggested_action": "observe_only"
    },
    {
      "code": "588220",
      "name": "科创100F",
      "category": "GROWTH",
      "score": 19.28,
      "price": 2.171,
      "pct": 6.16,
      "main_inflow": -43717189.0,
      "main_inflow_pct": -5.72,
      "ma5": 2.0954,
      "ma10": 2.1215,
      "ma20": 2.04445,
      "amount_ratio_20": null,
      "reason": "主力资金未转正；OBSERVE_ONLY",
      "trigger": "等待资金转正并站回MA5",
      "failure": "继续跌破MA10或放量长阴",
      "suggested_action": "observe_only"
    },
    {
      "code": "515880",
      "name": "通信ETF",
      "category": "SECTOR",
      "score": 14.82,
      "price": 0.807,
      "pct": 6.61,
      "main_inflow": 211918880.0,
      "main_inflow_pct": 2.98,
      "ma5": 0.775,
      "ma10": 0.8157,
      "ma20": 0.8467,
      "amount_ratio_20": null,
      "reason": "主力流入强度不足；OBSERVE_ONLY",
      "trigger": "等待资金转正并站回MA5",
      "failure": "继续跌破MA10或放量长阴",
      "suggested_action": "observe_only"
    },
    {
      "code": "510500",
      "name": "中证500ETF",
      "category": "CORE",
      "score": 11.67,
      "price": 8.804,
      "pct": 2.96,
      "main_inflow": -24629504.0,
      "main_inflow_pct": -0.48,
      "ma5": 8.7438,
      "ma10": 8.8777,
      "ma20": 8.79055,
      "amount_ratio_20": null,
      "reason": "主力资金未转正；OBSERVE_ONLY",
      "trigger": "等待资金转正并站回MA5",
      "failure": "继续跌破MA10或放量长阴",
      "suggested_action": "observe_only"
    },
    {
      "code": "512100",
      "name": "中证1000ETF",
      "category": "CORE",
      "score": 2.43,
      "price": 3.354,
      "pct": 1.95,
      "main_inflow": -120176384.0,
      "main_inflow_pct": -2.01,
      "ma5": 3.3862,
      "ma10": 3.4543,
      "ma20": 3.4670499999999995,
      "amount_ratio_20": null,
      "reason": "主力资金未转正；OBSERVE_ONLY",
      "trigger": "等待资金转正并站回MA5",
      "failure": "继续跌破MA10或放量长阴",
      "suggested_action": "observe_only"
    },
    {
      "code": "562500",
      "name": "机器人ETF",
      "category": "THEME",
      "score": 0.8,
      "price": 1.109,
      "pct": 2.31,
      "main_inflow": -58315024.0,
      "main_inflow_pct": -5.76,
      "ma5": 1.1364,
      "ma10": 1.1299,
      "ma20": 1.13155,
      "amount_ratio_20": null,
      "reason": "主力资金未转正；OBSERVE_ONLY",
      "trigger": "等待资金转正并站回MA5",
      "failure": "继续跌破MA10或放量长阴",
      "suggested_action": "observe_only"
    },
    {
      "code": "512890",
      "name": "红利低波ETF",
      "category": "DEFENSE",
      "score": -6.69,
      "price": 1.105,
      "pct": -1.34,
      "main_inflow": -132667424.0,
      "main_inflow_pct": -14.86,
      "ma5": 1.1062,
      "ma10": 1.0934000000000001,
      "ma20": 1.1122999999999998,
      "amount_ratio_20": null,
      "reason": "主力资金未转正；OBSERVE_ONLY",
      "trigger": "等待资金转正并站回MA5",
      "failure": "继续跌破MA10或放量长阴",
      "suggested_action": "observe_only"
    }
  ],
  "exclude": [
    {
      "code": "159915",
      "name": "创业板ETF",
      "category": "GROWTH",
      "score": 13.04,
      "price": 4.04,
      "pct": 4.47,
      "main_inflow": 378405200.0,
      "main_inflow_pct": 4.95,
      "ma5": 3.9692,
      "ma10": 4.097099999999999,
      "ma20": 4.12485,
      "amount_ratio_20": null,
      "reason": "跌破MA10；OBSERVE_ONLY",
      "trigger": "不触发",
      "failure": "今日不碰，盘后重新评估",
      "suggested_action": "observe_only"
    },
    {
      "code": "512000",
      "name": "券商ETF",
      "category": "SECTOR",
      "score": 9.9,
      "price": 0.542,
      "pct": 2.26,
      "main_inflow": 49370304.0,
      "main_inflow_pct": 3.54,
      "ma5": 0.5428000000000001,
      "ma10": 0.5429,
      "ma20": 0.5309,
      "amount_ratio_20": null,
      "reason": "跌破MA10；A_PULLBACK_WATCH",
      "trigger": "不触发",
      "failure": "今日不碰，盘后重新评估",
      "suggested_action": "observe_only"
    },
    {
      "code": "516020",
      "name": "化工ETF",
      "category": "SECTOR",
      "score": 0.72,
      "price": 0.856,
      "pct": -0.47,
      "main_inflow": 5873897.0,
      "main_inflow_pct": 3.47,
      "ma5": 0.8917999999999999,
      "ma10": 0.9109,
      "ma20": 0.9157500000000001,
      "amount_ratio_20": null,
      "reason": "跌破MA10；OBSERVE_ONLY",
      "trigger": "不触发",
      "failure": "今日不碰，盘后重新评估",
      "suggested_action": "observe_only"
    }
  ],
  "exit_queue": [],
  "position_stops": [],
  "backtest": {
    "total_signals": 0,
    "by_regime": {},
    "recent": []
  },
  "decision_reviews": {
    "total_reviews": 0,
    "by_label": {},
    "recent": []
  },
  "risk_notes": [
    "不自动下单",
    "不追高开",
    "首笔不超过计划仓位1/3",
    "TREND_DOWN只做有序退出"
  ]
}
